amplpower/__init__.py
amplpower/__main__.py
amplpower/cli.py
amplpower/core.py
amplpower/opf.mod
amplpower/utils.py
amplpower/data/case118.m
amplpower/data/case118Blumsack.m
amplpower/data/case14.m
amplpower/data/case30.m
amplpower/data/case300.m
amplpower/data/case39.m
amplpower/data/case5.m
amplpower/data/case57.m
amplpower/data/case9.m
amplpower/data/case9_Nacho.m
amplpower/data/case9_switching.m
amplpower/data/pglib_opf_case118_ieee.m
amplpower/data/pglib_opf_case14_ieee.m
amplpower/data/pglib_opf_case240_pserc.m
amplpower/data/pglib_opf_case300_ieee.m
amplpower/data/pglib_opf_case30_ieee.m
amplpower/data/pglib_opf_case57_ieee.m
amplpower/data/pglib_opf_case5_pjm.m
amplpower-0.0.42.dist-info/AUTHORS.rst
amplpower-0.0.42.dist-info/LICENSE
amplpower-0.0.42.dist-info/METADATA
amplpower-0.0.42.dist-info/WHEEL
amplpower-0.0.42.dist-info/entry_points.txt
amplpower-0.0.42.dist-info/top_level.txt
amplpower-0.0.42.dist-info/RECORD
